soong/__init__.py
soong/dml.py
soong/query.py
soong-0.6.0.dist-info/LICENSE
soong-0.6.0.dist-info/METADATA
soong-0.6.0.dist-info/WHEEL
soong-0.6.0.dist-info/top_level.txt
soong-0.6.0.dist-info/RECORD
