Metadata-Version: 2.1
Name: soong
Version: 0.6.0
Summary: PostgreSQL utility library for AWS Lambda
Home-page: https://github.com/eladkehat/soong
Author: Elad Kehat
Author-email: eladkehat@gmail.com
License: MIT
Keywords: serverless aws labmda postgresql pgsql
Platform: UNKNOWN
Classifier: Development Status :: 3 - Alpha
Classifier: Intended Audience :: Developers
Classifier: License :: OSI Approved :: MIT License
Classifier: Operating System :: OS Independent
Classifier: Programming Language :: Python :: 3.7
Classifier: Topic :: Database
Classifier: Typing :: Typed
Requires-Python: >=3.7
Requires-Dist: boto3 (~=1.7)
Requires-Dist: psycopg2-binary (~=2.7)
